LICENSE.rtf
README.md
setup.py
topsis/__init__.py
topsis/topsis.py
topsis_sarthaksachdeva_102203493.egg-info/PKG-INFO
topsis_sarthaksachdeva_102203493.egg-info/SOURCES.txt
topsis_sarthaksachdeva_102203493.egg-info/dependency_links.txt
topsis_sarthaksachdeva_102203493.egg-info/requires.txt
topsis_sarthaksachdeva_102203493.egg-info/top_level.txt